ordered/__init__.py
ordered/ordered.py
ordered-0.0.2.dist-info/AUTHORS.rst
ordered-0.0.2.dist-info/LICENSE.txt
ordered-0.0.2.dist-info/METADATA
ordered-0.0.2.dist-info/WHEEL
ordered-0.0.2.dist-info/top_level.txt
ordered-0.0.2.dist-info/RECORD
