Metadata-Version: 2.1
Name: ordered
Version: 0.0.2
Summary: Entropy-controlled contexts in Python
Home-page: https://github.com/hyperc-ai/ordered/
Author: Andrew Gree
Author-email: andrew@hyperc.com
License: MIT
Project-URL: Documentation, https://github.com/hyperc-ai/ordered/
Project-URL: Source, https://github.com/hyperc-ai/ordered/
Platform: linux
Classifier: Development Status :: 3 - Alpha
Classifier: Programming Language :: Python
Requires-Python: >=3.8
License-File: LICENSE.txt
License-File: AUTHORS.rst
Requires-Dist: importlib-metadata
Requires-Dist: python-version (>="3.8")
Requires-Dist: hyperc
Provides-Extra: testing
Requires-Dist: setuptools ; extra == 'testing'
Requires-Dist: pytest ; extra == 'testing'
Requires-Dist: pytest-cov ; extra == 'testing'
